tajm2/__init__.py
tajm2/base_model.py
tajm2/constants.py
tajm2/custom_inputs.py
tajm2/custom_validators.py
tajm2/layout.tcss
tajm2/tajm2.py
tajm2/time_slot.py
tajm2-0.0.1.dist-info/METADATA
tajm2-0.0.1.dist-info/WHEEL
tajm2-0.0.1.dist-info/licenses/LICENSE
tajm2-0.0.1.dist-info/RECORD
