Metadata-Version: 2.1
Name: tajm2
Version: 0.0.1
Summary: tajm2 is a command line GUI tool built on Textual to manage time slots.
Project-URL: Homepage, https://github.com/davsva/tajm2
Project-URL: Issues, https://github.com/davsva/tajm2/issues
Author-email: David Svanberg <david.svanberg@gmail.com>
License-File: LICENSE
Classifier: License :: OSI Approved :: MIT License
Classifier: Operating System :: OS Independent
Classifier: Programming Language :: Python :: 3
Requires-Python: >=3.8
